main.py
pubmed_mcp_tool-0.1.0.dist-info/METADATA
pubmed_mcp_tool-0.1.0.dist-info/WHEEL
pubmed_mcp_tool-0.1.0.dist-info/top_level.txt
pubmed_mcp_tool-0.1.0.dist-info/RECORD
