Metadata-Version: 2.4
Name: pubmed-mcp-tool
Version: 0.1.0
Summary: PubMed文献检索MCP工具
Requires-Python: >=3.13
Requires-Dist: fastmcp>=2.12.4
Requires-Dist: httpx>=0.28.1
